README.md
setup.py
script/make_entity_info.py
script/make_test_dir.py
script/oidc_setup.py
script/optest.py
src/oidctest/__init__.py
src/oidctest/app_conf.py
src/oidctest/ass_port.py
src/oidctest/endpoints.py
src/oidctest/file_system.py
src/oidctest/prof_util.py
src/oidctest/regalg.py
src/oidctest/response_encoder.py
src/oidctest/session.py
src/oidctest/site_setup.py
src/oidctest/testfunc.py
src/oidctest/tool.py
src/oidctest/utils.py
src/oidctest.egg-info/PKG-INFO
src/oidctest.egg-info/SOURCES.txt
src/oidctest.egg-info/dependency_links.txt
src/oidctest.egg-info/not-zip-safe
src/oidctest.egg-info/requires.txt
src/oidctest.egg-info/top_level.txt
src/oidctest/cp/__init__.py
src/oidctest/cp/log_handler.py
src/oidctest/cp/op.py
src/oidctest/cp/op_handler.py
src/oidctest/cp/setup.py
src/oidctest/cp/test_list.py
src/oidctest/op/__init__.py
src/oidctest/op/check.py
src/oidctest/op/client.py
src/oidctest/op/func.py
src/oidctest/op/oper.py
src/oidctest/op/profiles.py
src/oidctest/optt/__init__.py
src/oidctest/rp/__init__.py
src/oidctest/rp/func.py
src/oidctest/rp/instance.py
src/oidctest/rp/parse_conf.py
src/oidctest/rp/pathmap.py
src/oidctest/rp/prof_util.py
src/oidctest/rp/provider.py
src/oidctest/tt/__init__.py
src/oidctest/tt/action.py
src/oidctest/tt/app.py
src/oidctest/tt/entity.py
src/oidctest/tt/instance.py
src/oidctest/tt/rest.py